{
  "timestamp": "2026-05-28T11:13:16.239702",
  "phase": "w3-integration",
  "stages": {
    "guardian": {
      "total": 100,
      "accepted": 99,
      "rejected": 1,
      "pass_rate": 0.99
    },
    "sib": {
      "RSR": 0.9010430254052236,
      "SUR": 0.9717267223017292,
      "PHL": 1800,
      "status": "PASS"
    },
    "fairness": {
      "gini": 0.25,
      "capture_ratio": 0.3,
      "status": "PASS"
    },
    "destruction": {
      "total_entries": 99,
      "audited_entries": 10,
      "all_zeroed": true,
      "status": "PASS"
    },
    "redistribution": {
      "total_pool": 10000.0,
      "creators": 99,
      "avg_compensation": 101.01010101010101,
      "status": "PASS"
    }
  },
  "overall_status": "PASS"
}